text2vec2onnx/__init__.py
text2vec2onnx/sentence_model.py
text2vec2onnx/similarity.py
text2vec2onnx/version.py
text2vec2onnx-1.0.0.dist-info/LICENSE
text2vec2onnx-1.0.0.dist-info/METADATA
text2vec2onnx-1.0.0.dist-info/WHEEL
text2vec2onnx-1.0.0.dist-info/top_level.txt
text2vec2onnx-1.0.0.dist-info/RECORD
