Metadata-Version: 2.1
Name: text2vec2onnx
Version: 1.0.0
Summary: Text to vector Tool, encode text
Home-page: https://github.com/GanymedeNil/text2vec-onnx
Author: GanymedeNil
Author-email: GanymedeNil@gmail.com
License: Apache License 2.0
Keywords: word embedding,text2vec,onnx,Chinese Text Similarity Calculation Tool,similarity
Classifier: Development Status :: 5 - Production/Stable
Classifier: Intended Audience :: Developers
Classifier: Intended Audience :: Education
Classifier: Intended Audience :: Science/Research
Classifier: License :: OSI Approved :: Apache Software License
Classifier: Operating System :: OS Independent
Classifier: Programming Language :: Python :: 3
Classifier: Topic :: Scientific/Engineering :: Artificial Intelligence
Requires-Python: >=3.8.0
License-File: LICENSE
Requires-Dist: tokenizers
Requires-Dist: numpy <=1.26.4
Provides-Extra: cpu
Requires-Dist: onnxruntime ; extra == 'cpu'
Provides-Extra: gpu
Requires-Dist: onnxruntime-gpu ; extra == 'gpu'
